hipscatalog_gen/__init__.py
hipscatalog_gen/cli.py
hipscatalog_gen/config.py
hipscatalog_gen/py.typed
hipscatalog_gen/assets/telemetry.schema.json
hipscatalog_gen/cluster/__init__.py
hipscatalog_gen/cluster/runtime.py
hipscatalog_gen/healpix/__init__.py
hipscatalog_gen/healpix/densmap.py
hipscatalog_gen/io/__init__.py
hipscatalog_gen/io/input.py
hipscatalog_gen/io/output.py
hipscatalog_gen/mag_global/__init__.py
hipscatalog_gen/mag_global/pipeline.py
hipscatalog_gen/pipeline/__init__.py
hipscatalog_gen/pipeline/common.py
hipscatalog_gen/pipeline/logging_utils.py
hipscatalog_gen/pipeline/main.py
hipscatalog_gen/pipeline/modes.py
hipscatalog_gen/pipeline/params.py
hipscatalog_gen/pipeline/structure.py
hipscatalog_gen/pipeline/validation.py
hipscatalog_gen/score_density_hybrid/__init__.py
hipscatalog_gen/score_density_hybrid/pipeline.py
hipscatalog_gen/score_global/__init__.py
hipscatalog_gen/score_global/pipeline.py
hipscatalog_gen/selection/__init__.py
hipscatalog_gen/selection/common.py
hipscatalog_gen/selection/levels.py
hipscatalog_gen/selection/score.py
hipscatalog_gen/selection/slicing.py
hipscatalog_gen/utils/__init__.py
hipscatalog_gen-0.1.1.dist-info/licenses/LICENSE
hipscatalog_gen-0.1.1.dist-info/METADATA
hipscatalog_gen-0.1.1.dist-info/WHEEL
hipscatalog_gen-0.1.1.dist-info/entry_points.txt
hipscatalog_gen-0.1.1.dist-info/top_level.txt
hipscatalog_gen-0.1.1.dist-info/RECORD
