Metadata-Version: 2.4
Name: hipscatalog-gen
Version: 0.1.1
Author-email: Luigi Lucas de Carvalho Silva <luigi.silva@linea.org.br>
License-Expression: MIT
Project-URL: Homepage, https://github.com/linea-it/hipscatalog_gen
Project-URL: Documentation, https://github.com/linea-it/hipscatalog_gen
Project-URL: Bug Tracker, https://github.com/linea-it/hipscatalog_gen/issues
Project-URL: Source Code, https://github.com/linea-it/hipscatalog-gen
Classifier: Development Status :: 4 - Beta
Classifier: Intended Audience :: Developers
Classifier: Intended Audience :: Science/Research
Classifier: Operating System :: OS Independent
Classifier: Programming Language :: Python
Classifier: Programming Language :: Python :: 3
Classifier: Programming Language :: Python :: 3.11
Classifier: Programming Language :: Python :: 3.12
Classifier: Programming Language :: Python :: 3.13
Requires-Python: >=3.11
License-File: LICENSE
Requires-Dist: numpy<3.0,>=2.0
Requires-Dist: pandas<3.0,>=2.1
Requires-Dist: pyarrow<23,>=14
Requires-Dist: dask<2026.0,>=2024.8.0
Requires-Dist: distributed<2026.0,>=2024.8.0
Requires-Dist: astropy<8,>=6
Requires-Dist: healpy<2.0,>=1.17
Requires-Dist: mocpy<1.0,>=0.12
Requires-Dist: hats<1.0,>=0.6
Requires-Dist: lsdb<1.0,>=0.6
Requires-Dist: pyyaml<7,>=6
Requires-Dist: scipy>=1.13
Provides-Extra: slurm
Requires-Dist: dask-jobqueue<1.0,>=0.8; extra == "slurm"
Provides-Extra: s3
Requires-Dist: s3fs<2026.0,>=2024.6; extra == "s3"
Provides-Extra: dev
Requires-Dist: asv[virtualenv]==0.6.5; extra == "dev"
Requires-Dist: jupyter; extra == "dev"
Requires-Dist: nbconvert<8,>=7.16.6; extra == "dev"
Requires-Dist: mypy; extra == "dev"
Requires-Dist: pre-commit; extra == "dev"
Requires-Dist: pytest; extra == "dev"
Requires-Dist: pytest-cov; extra == "dev"
Requires-Dist: ruff; extra == "dev"
Provides-Extra: docs
Requires-Dist: sphinx<10,>=7.2; extra == "docs"
Requires-Dist: sphinx-rtd-theme<4,>=3.0; extra == "docs"
Requires-Dist: myst-parser<5,>=2.0; extra == "docs"
Requires-Dist: sphinx-autodoc-typehints<4,>=2.0; extra == "docs"
Dynamic: license-file
